mailwizz/__init__.py
mailwizz/base.py
mailwizz/client.py
mailwizz/config.py
mailwizz/request.py
mailwizz/endpoint/__init__.py
mailwizz/endpoint/campaign_bounces.py
mailwizz/endpoint/campaigns.py
mailwizz/endpoint/campaigns_tracking.py
mailwizz/endpoint/countries.py
mailwizz/endpoint/customers.py
mailwizz/endpoint/list_fields.py
mailwizz/endpoint/list_segments.py
mailwizz/endpoint/list_subscribers.py
mailwizz/endpoint/lists.py
mailwizz/endpoint/templates.py
mailwizz/endpoint/transactional_emails.py
mailwizz_python_sdk-1.0.3.dist-info/LICENSE
mailwizz_python_sdk-1.0.3.dist-info/METADATA
mailwizz_python_sdk-1.0.3.dist-info/WHEEL
mailwizz_python_sdk-1.0.3.dist-info/top_level.txt
mailwizz_python_sdk-1.0.3.dist-info/RECORD
