Metadata-Version: 2.1
Name: mailwizz-python-sdk
Version: 1.0.3
Summary: This repository contains the Python SDK for MailWizz EMA.
Home-page: https://www.mailwizz.com
Author: twisted1919
Author-email: support@mailwizz.com
License: MIT
Classifier: Programming Language :: Python :: 3
Classifier: License :: OSI Approved :: MIT License
Classifier: Operating System :: OS Independent
License-File: LICENSE
Requires-Dist: multidimensional-urlencode >=0.0.4
Requires-Dist: requests >=2.22.0
Requires-Dist: urllib3 >=1.25.3
